vien/__init__.py
vien/__main__.py
vien/_bash_runner.py
vien/_call_funcs.py
vien/_cmdexe_escape_args.py
vien/_colors.py
vien/_common.py
vien/_constants.py
vien/_exceptions.py
vien/_main.py
vien/_parsed_args.py
vien/_parsed_call.py
vien-8.1.4.dist-info/LICENSE
vien-8.1.4.dist-info/METADATA
vien-8.1.4.dist-info/WHEEL
vien-8.1.4.dist-info/entry_points.txt
vien-8.1.4.dist-info/top_level.txt
vien-8.1.4.dist-info/RECORD
