Metadata-Version: 2.1
Name: vien
Version: 8.1.4
Summary: Command-line tool for managing Python virtual environments
Home-page: https://github.com/rtmigo/vien_py
Author: Artëm IG
Author-email: ortemeo@gmail.com
License: BSD-3-Clause
Keywords: virtual-environment,venv,virtualenv,python,command-line,shell,terminal,bash,run,create,delete,execute
Platform: UNKNOWN
Classifier: Development Status :: 4 - Beta
Classifier: Intended Audience :: Developers
Classifier: License :: OSI Approved :: BSD License
Classifier: Programming Language :: Python :: 3.7
Classifier: Programming Language :: Python :: 3.8
Classifier: Programming Language :: Python :: 3.9
Classifier: Programming Language :: Python :: 3.10
Classifier: Environment :: Console
Classifier: Typing :: Typed
Classifier: Topic :: Software Development :: Build Tools
Classifier: Operating System :: POSIX
Requires-Python: >=3.7
License-File: LICENSE
